{
  "market": {
    "generated_at": "2026-05-13 16:40 CEST",
    "next_update": "Siguiente ejecucion programada",
    "market_cap_t": 2.742,
    "market_cap_change_24h": 0.7,
    "volume_24h_b": 103.159,
    "btc_dominance": 58.2,
    "eth_dominance": 9.96,
    "altseason_index": 35,
    "altseason_label": "Bitcoin Season",
    "altcoin_dominance": 31.84,
    "open_interest_b": null,
    "derivatives_volume_b": null,
    "liquidations_m": null,
    "fear_greed": 47,
    "fear_greed_label": "Neutral (47)",
    "sentiment_ai": "Neutral con sesgo defensivo; liderazgo BTC",
    "risk_level": "Moderado/alto",
    "macro_state": "CPI y PPI repuntan; el filtro macro sigue siendo exigente",
    "regime": "BTC conserva liderazgo y las altcoins mejoran de forma selectiva, pero sin breadth suficiente para validar altseason"
  },
  "assets": [
    {
      "symbol": "BTC",
      "name": "Bitcoin",
      "price": 79732.05,
      "change_24h": -1.3,
      "change_7d": -2.4,
      "volume_24h_b": 41.81,
      "market_cap_b": 1596.752,
      "low_24h": 79611.24,
      "high_24h": 81262.79,
      "low_7d": 79467.28,
      "high_7d": 82145.66,
      "oi_b": null,
      "oi_change_24h": null,
      "funding_rate": null,
      "liquidations_m": null
    },
    {
      "symbol": "ETH",
      "name": "Ethereum",
      "price": 2332.01,
      "change_24h": 0.6,
      "change_7d": 1.0,
      "volume_24h_b": 12.764,
      "market_cap_b": 281.464,
      "low_24h": 2302.74,
      "high_24h": 2336.75,
      "low_7d": 2261.45,
      "high_7d": 2373.93,
      "oi_b": null,
      "oi_change_24h": null,
      "funding_rate": null,
      "liquidations_m": null
    },
    {
      "symbol": "SOL",
      "name": "Solana",
      "price": 93.33,
      "change_24h": 1.1,
      "change_7d": 11.1,
      "volume_24h_b": 3.316,
      "market_cap_b": 53.905,
      "low_24h": 91.79,
      "high_24h": 94.02,
      "low_7d": 83.64,
      "high_7d": 93.71,
      "oi_b": null,
      "oi_change_24h": null,
      "funding_rate": null,
      "liquidations_m": null
    },
    {
      "symbol": "BNB",
      "name": "BNB",
      "price": 650.28,
      "change_24h": 2.1,
      "change_7d": 5.7,
      "volume_24h_b": 0.946,
      "market_cap_b": 87.725,
      "low_24h": 635.17,
      "high_24h": 655.61,
      "low_7d": 615.44,
      "high_7d": 657.11,
      "oi_b": null,
      "oi_change_24h": null,
      "funding_rate": null,
      "liquidations_m": null
    },
    {
      "symbol": "XRP",
      "name": "XRP",
      "price": 1.42,
      "change_24h": 0.0,
      "change_7d": 2.1,
      "volume_24h_b": 1.405,
      "market_cap_b": 87.833,
      "low_24h": 1.41,
      "high_24h": 1.43,
      "low_7d": 1.38,
      "high_7d": 1.45,
      "oi_b": null,
      "oi_change_24h": null,
      "funding_rate": null,
      "liquidations_m": null
    },
    {
      "symbol": "ADA",
      "name": "Cardano",
      "price": 0.2703,
      "change_24h": 2.6,
      "change_7d": 9.0,
      "volume_24h_b": 0.254,
      "market_cap_b": 9.991,
      "low_24h": 0.2693,
      "high_24h": 0.2775,
      "low_7d": 0.2611,
      "high_7d": 0.2871,
      "oi_b": null,
      "oi_change_24h": null,
      "funding_rate": null,
      "liquidations_m": null
    },
    {
      "symbol": "DOGE",
      "name": "Dogecoin",
      "price": 0.1074,
      "change_24h": -3.6,
      "change_7d": -0.7,
      "volume_24h_b": 1.351,
      "market_cap_b": 16.534,
      "low_24h": 0.1058,
      "high_24h": 0.1115,
      "low_7d": 0.1062,
      "high_7d": 0.1165,
      "oi_b": null,
      "oi_change_24h": null,
      "funding_rate": null,
      "liquidations_m": null
    }
  ],
  "news": [
    {
      "title": "Charles Schwab inicia el despliegue de trading directo de BTC y ETH",
      "source": "Cointelegraph",
      "time": "13 May 2026",
      "impact": "Alto",
      "summary": "Amplia la distribucion minorista e institucional al integrar cripto junto a acciones y ETFs dentro de la misma cuenta de corretaje."
    },
    {
      "title": "Ethereum activa Clear Signing para reducir el riesgo de blind signing",
      "source": "Cointelegraph",
      "time": "13 May 2026",
      "impact": "Alto",
      "summary": "Ledger, Trezor, MetaMask y otros participantes adoptan una capa de seguridad que mejora la legibilidad de las firmas y reduce riesgo operativo."
    },
    {
      "title": "JPMorgan registra un money market tokenizado para emisores de stablecoins",
      "source": "Cointelegraph",
      "time": "13 May 2026",
      "impact": "Medio/alto",
      "summary": "La iniciativa sobre Ethereum refuerza la tesis de tokenizacion institucional y acerca el uso de reservas reguladas a la infraestructura onchain."
    },
    {
      "title": "Galaxy y Sharplink planean un fondo institucional onchain con $125M",
      "source": "Nasdaq",
      "time": "11 May 2026",
      "impact": "Medio/alto",
      "summary": "El vehiculo usaria capital ligado a la tesoreria en ETH para estrategias de rendimiento onchain y apunta a consolidar la narrativa institucional de Ethereum."
    }
  ],
  "macro": [
    {
      "title": "CPI de abril en EE. UU.",
      "when": "Publicado 12 May 2026",
      "detail": "0.6% mensual y 3.8% interanual; energia explico mas del 40% del avance mensual del IPC general.",
      "impact": "Bearish tactico para multiples de riesgo"
    },
    {
      "title": "PPI de abril en EE. UU.",
      "when": "Publicado 13 May 2026",
      "detail": "Final demand +1.4% mensual y +6.0% interanual; confirma presion aguas arriba tras el dato de CPI.",
      "impact": "Aumenta sensibilidad de cripto a yields y dolar"
    },
    {
      "title": "Empleo de abril en EE. UU.",
      "when": "Publicado 08 May 2026",
      "detail": "Las payrolls subieron en 115.000 y la tasa de desempleo quedo en 4.3%.",
      "impact": "Mercado laboral todavia resiliente; reduce margen para un giro dovish rapido"
    },
    {
      "title": "FOMC",
      "when": "16-17 Jun 2026",
      "detail": "Proxima reunion de politica monetaria de la Fed, con SEP incluida.",
      "impact": "Evento macro principal del proximo mes"
    },
    {
      "title": "ECB",
      "when": "11 Jun 2026",
      "detail": "Siguiente rueda de prensa monetaria del BCE tras la decision de abril de mantener tipos sin cambios.",
      "impact": "Relevante para EUR, liquidez global y apetito por riesgo"
    }
  ],
  "alerts": [
    {
      "level": "Alta",
      "title": "CPI y PPI vuelven a endurecer el telon macro",
      "detail": "La combinacion de IPC y precios al productor reduce margen para un repricing dovish y eleva la sensibilidad de BTC a yields y dolar."
    },
    {
      "level": "Media",
      "title": "Rupturas aun sin breadth suficiente fuera de BTC",
      "detail": "El indice de altseason marca 35/100: hay mejora selectiva, pero no una rotacion amplia y sostenida hacia beta alta."
    },
    {
      "level": "Media",
      "title": "Distribucion institucional mejora, pero no garantiza follow-through",
      "detail": "Schwab, JPMorgan y Galaxy sostienen la narrativa institucional, aunque el mercado todavia exige confirmacion tecnica para extender el rally."
    }
  ],
  "scenarios": [
    {
      "name": "Alcista",
      "prob": 25,
      "targets": "BTC 81.3k-82.1k | ETH 2.35k-2.40k | SOL 94-98",
      "risk": "Moderado",
      "confidence": "Media",
      "trigger": "BTC recupera 81k con compresion de volatilidad y mejora del sentimiento mas alla de las majors."
    },
    {
      "name": "Neutral",
      "prob": 50,
      "targets": "BTC 79.5k-81.3k | ETH 2.30k-2.36k | SOL 91-94",
      "risk": "Controlado",
      "confidence": "Alta",
      "trigger": "El mercado absorbe CPI/PPI sin ruptura direccional y mantiene foco en tokenizacion e institucionales."
    },
    {
      "name": "Bajista",
      "prob": 25,
      "targets": "BTC 78.8k-79.4k | ETH 2.26k | SOL 88-91",
      "risk": "Elevado",
      "confidence": "Media",
      "trigger": "Nueva subida de yields o rechazo bajo 81k con perdida de soportes tacticos en BTC y ETH."
    }
  ]
}
